<?xml version="1.0" encoding="utf-8"?><toc><breadcrumbs><li><a href="d060485c-ae14-71b2-40f1-47eded9ebe2c.htm">Docs</a></li><li><a href="f81fe57e-7efa-bc07-8daa-514033138c7d.htm">Machina.<wbr />Controllers</a></li><li><a href="00d0efc5-06ed-b93d-9af1-4e99bf33d3aa.htm">Control<wbr />Manager</a></li></breadcrumbs><tocItems><li><a id="981907a1-c8b6-5744-6c34-469b230976c8" href="981907a1-c8b6-5744-6c34-469b230976c8.htm">Constructor</a></li><li><a id="650c4f9c-977d-d4e3-1da4-d1a1285980c9" class="has-submenu" href="650c4f9c-977d-d4e3-1da4-d1a1285980c9.htm"><span data-tocFile="../toc/IDBBC.xml" class="icon toggle" onclick="ToggleExpandCollapse(this); return false;"><i class="fa fa-angle-right"> </i></span>Properties</a><ul class="toc-menu is-hidden"> </ul></li><li><a id="5029783a-6a8e-2eda-be45-0b1e9f0af9c2" class="has-submenu" href="5029783a-6a8e-2eda-be45-0b1e9f0af9c2.htm"><span data-tocFile="../toc/IDCBC.xml" class="icon toggle" onclick="ToggleExpandCollapse(this); return false;"><i class="fa fa-angle-right"> </i></span>Methods</a><ul class="toc-menu is-hidden"> </ul></li><li><a id="7e204d23-2a01-5c39-0e79-e8f20e6c6c9d" class="has-submenu" href="7e204d23-2a01-5c39-0e79-e8f20e6c6c9d.htm"><span data-tocFile="../toc/IDDBC.xml" class="icon toggle" onclick="ToggleExpandCollapse(this); return false;"><i class="fa fa-angle-right"> </i></span>Fields</a><ul class="toc-menu is-hidden"> </ul></li></tocItems></toc>